doomsday/__init__.py
doomsday/clock.py
doomsday_clock_status-0.1.7.dist-info/LICENSE
doomsday_clock_status-0.1.7.dist-info/METADATA
doomsday_clock_status-0.1.7.dist-info/WHEEL
doomsday_clock_status-0.1.7.dist-info/top_level.txt
doomsday_clock_status-0.1.7.dist-info/RECORD
