Metadata-Version: 2.1
Name: doomsday-clock-status
Version: 0.1.7
Summary: A package to get the current doomsday-clock time.
Home-page: https://github.com/cookie0o/doomsday-clock
Author: cookie0_o
Author-email: therealcookie@waifu.club
Classifier: Programming Language :: Python :: 3
Classifier: License :: OSI Approved :: MIT License
Classifier: Operating System :: OS Independent
License-File: LICENSE
